__init__.py
cache_coordinator_pb2.py
cache_coordinator_pb2_grpc.py
super_client.py
super_client-14.0.0.dist-info/METADATA
super_client-14.0.0.dist-info/WHEEL
super_client-14.0.0.dist-info/top_level.txt
super_client-14.0.0.dist-info/RECORD
