Metadata-Version: 2.1
Name: super_client
Version: 14.0.0
Summary: A small example package
Author-email: Example Author <author@example.com>
Classifier: Programming Language :: Python :: 3
Classifier: License :: OSI Approved :: MIT License
Classifier: Operating System :: OS Independent
Requires-Python: >=3.8
Requires-Dist: grpcio-tools
